hatch_simple_cython/__init__.py
hatch_simple_cython/hooks.py
hatch_simple_cython/plugin.py
hatch_simple_cython/py.typed
hatch_simple_cython-0.1.0b3.dist-info/METADATA
hatch_simple_cython-0.1.0b3.dist-info/WHEEL
hatch_simple_cython-0.1.0b3.dist-info/entry_points.txt
hatch_simple_cython-0.1.0b3.dist-info/licenses/LICENSE
hatch_simple_cython-0.1.0b3.dist-info/RECORD
