Metadata-Version: 2.4
Name: hatch-simple-cython
Version: 0.1.0b3
Summary: A simplified Cython build hook plugin for Hatch
Project-URL: Documentation, https://github.com/Sun-ZhenXing/hatch-simple-cython#readme
Project-URL: Issues, https://github.com/Sun-ZhenXing/hatch-simple-cython/issues
Project-URL: Source, https://github.com/Sun-ZhenXing/hatch-simple-cython
License-File: LICENSE
Classifier: Development Status :: 4 - Beta
Classifier: Framework :: Hatch
Classifier: Programming Language :: Python
Classifier: Programming Language :: Python :: 3.10
Classifier: Programming Language :: Python :: 3.11
Classifier: Programming Language :: Python :: 3.12
Classifier: Programming Language :: Python :: Implementation :: CPython
Requires-Python: >=3.10
Requires-Dist: cython>=3.0.0
Requires-Dist: hatchling>=1.15.0
Requires-Dist: setuptools>=80.0.0
Requires-Dist: tomli>=2.3.0; python_version < '3.11'
